calm/dsl/__init__.py
calm/dsl/constants.py
calm/dsl/api/__init__.py
calm/dsl/api/access_control_policy.py
calm/dsl/api/app_icons.py
calm/dsl/api/app_protection_policy.py
calm/dsl/api/application.py
calm/dsl/api/approval.py
calm/dsl/api/approval_request.py
calm/dsl/api/blueprint.py
calm/dsl/api/connection.py
calm/dsl/api/directory_service.py
calm/dsl/api/endpoint.py
calm/dsl/api/environment.py
calm/dsl/api/global_variable.py
calm/dsl/api/groups_api.py
calm/dsl/api/handle.py
calm/dsl/api/job.py
calm/dsl/api/library_tasks.py
calm/dsl/api/marketplace.py
calm/dsl/api/network_group.py
calm/dsl/api/nutanix_task.py
calm/dsl/api/policy.py
calm/dsl/api/policy_action_type.py
calm/dsl/api/policy_attributes.py
calm/dsl/api/policy_event.py
calm/dsl/api/project.py
calm/dsl/api/provider.py
calm/dsl/api/quotas.py
calm/dsl/api/resource.py
calm/dsl/api/resource_type.py
calm/dsl/api/role.py
calm/dsl/api/runbook.py
calm/dsl/api/setting.py
calm/dsl/api/showback.py
calm/dsl/api/tunnel.py
calm/dsl/api/user.py
calm/dsl/api/user_group.py
calm/dsl/api/util.py
calm/dsl/api/version.py
calm/dsl/api/vm_recovery_point.py
calm/dsl/builtins/__init__.py
calm/dsl/builtins/models/__init__.py
calm/dsl/builtins/models/account.py
calm/dsl/builtins/models/account_auth.py
calm/dsl/builtins/models/account_resources.py
calm/dsl/builtins/models/action.py
calm/dsl/builtins/models/ahv_account.py
calm/dsl/builtins/models/ahv_recovery_vm.py
calm/dsl/builtins/models/ahv_vm.py
calm/dsl/builtins/models/ahv_vm_cluster.py
calm/dsl/builtins/models/ahv_vm_disk.py
calm/dsl/builtins/models/ahv_vm_gc.py
calm/dsl/builtins/models/ahv_vm_gpu.py
calm/dsl/builtins/models/ahv_vm_nic.py
calm/dsl/builtins/models/ahv_vm_vpc.py
calm/dsl/builtins/models/app_edit.py
calm/dsl/builtins/models/app_protection.py
calm/dsl/builtins/models/approver_set.py
calm/dsl/builtins/models/aws_account.py
calm/dsl/builtins/models/aws_c2s_account.py
calm/dsl/builtins/models/azure_account.py
calm/dsl/builtins/models/blueprint.py
ntnx_ncm_dsl-4.3.0.1.dist-info/LICENSE
ntnx_ncm_dsl-4.3.0.1.dist-info/METADATA
ntnx_ncm_dsl-4.3.0.1.dist-info/WHEEL
ntnx_ncm_dsl-4.3.0.1.dist-info/entry_points.txt
ntnx_ncm_dsl-4.3.0.1.dist-info/top_level.txt
ntnx_ncm_dsl-4.3.0.1.dist-info/RECORD
