Metadata-Version: 2.1
Name: ntnx-ncm-dsl
Version: 4.3.0.1
Summary: NCM Self Service DSL for blueprints
Author-email: Nutanix <nucalm@nutanix.com>
License: 
Project-URL: Homepage, https://github.com/nutanix/calm-dsl
Keywords: calm,blueprints,dsl
Classifier: Development Status :: 3 - Alpha
Classifier: Environment :: Console
Classifier: Intended Audience :: Developers
Classifier: License :: OSI Approved :: Apache Software License
Classifier: Natural Language :: English
Classifier: Operating System :: OS Independent
Classifier: Programming Language :: Python :: 3.8
Classifier: Programming Language :: Python :: 3.9
Classifier: Programming Language :: Python :: 3.10
Classifier: Programming Language :: Python :: 3.11
Requires-Python: >=3.8
License-File: LICENSE
Requires-Dist: ruamel.yaml ==0.16.12
Requires-Dist: jinja2 ==3.0.3
Requires-Dist: jsonref ==0.2
Requires-Dist: bidict ==0.18.0
Requires-Dist: requests ==2.27.0
Requires-Dist: requests-toolbelt ==0.9.1
Requires-Dist: docopt ==0.6.2
Requires-Dist: PTable ==0.9.2
Requires-Dist: Click ==8.0.4
Requires-Dist: click-completion ==0.5.2
Requires-Dist: click-didyoumean ==0.0.3
Requires-Dist: click-repl ==0.2.0
Requires-Dist: colorama ==0.4.1
Requires-Dist: arrow ==0.15.1
Requires-Dist: jsonschema ==3.2.0
Requires-Dist: anytree ==2.8.0
Requires-Dist: asciimatics >=1.13.0
Requires-Dist: peewee ==3.10.0
Requires-Dist: pycryptodome ==3.19.1
Requires-Dist: scrypt ==0.9.4
Requires-Dist: schema ==0.7.1
Requires-Dist: colorlog ==5.0.1
Requires-Dist: black ==22.6.0
Requires-Dist: importlib-metadata ==4.6.0
Requires-Dist: pytz ==2022.7.1
Requires-Dist: pillow ==10.3.0
Requires-Dist: backports.zoneinfo ==0.2.1 ; python_version < "3.9"
Requires-Dist: pyyaml <=6.0.1 ; python_version < "3.9"
